zebrastream/io/__init__.py
zebrastream/io/_core.py
zebrastream/io/_exceptions.py
zebrastream/io/file.py
zebrastream/io/py.typed
zebrastream_io-0.3.0.dist-info/METADATA
zebrastream_io-0.3.0.dist-info/WHEEL
zebrastream_io-0.3.0.dist-info/licenses/LICENSE
zebrastream_io-0.3.0.dist-info/RECORD
