Metadata-Version: 2.4
Name: zebrastream-io
Version: 0.3.0
Summary: A Pythonic client library for streaming data with ZebraStream.
License-File: LICENSE
Author: Johannes Dröge
Author-email: p5p129dw@parsimonit.com
Requires-Python: >=3.10
Classifier: Programming Language :: Python :: 3
Classifier: Programming Language :: Python :: 3.10
Classifier: Programming Language :: Python :: 3.11
Classifier: Programming Language :: Python :: 3.12
Classifier: Programming Language :: Python :: 3.13
Classifier: Programming Language :: Python :: 3.14
Requires-Dist: aiohttp (>=3.12.14,<4.0.0)
Requires-Dist: anyio (>=4.9.0,<5.0.0)
Requires-Dist: typer (>=0.16.0,<0.17.0)
